{"abilities":[{"ability_id":"ABILITY_ADAPTABILITY","name":"Adaptability","effect":"Powers up moves of the same type.","pokemon_count":3,"notes":"Imported from Pokemon_Abilities source","source":"https://www.serebii.net/pokedex-champions/","confidenceStatus":"Needs Champions Confirmation","confidenceReason":"Existing local data preserved; official Pokémon Champions confirmation still required before treating as verified.","requiresOfficialReview":true,"strictModeEligible":false},{"ability_id":"ABILITY_AERILATE","name":"Aerilate","effect":"Normal-type moves become Flying-type moves.","pokemon_count":1,"notes":"Imported from Pokemon_Abilities source","source":"https://www.serebii.net/pokedex-champions/","confidenceStatus":"Needs Champions Confirmation","confidenceReason":"Existing local data preserved; official Pokémon Champions confirmation still required before treating as verified.","requiresOfficialReview":true,"strictModeEligible":false},{"ability_id":"ABILITY_AFTERMATH","name":"Aftermath","effect":"Damages the foe landing the finishing hit.","pokemon_count":1,"notes":"Imported from Pokemon_Abilities source","source":"https://www.serebii.net/pokedex-champions/","confidenceStatus":"Needs Champions Confirmation","confidenceReason":"Existing local data preserved; official Pokémon Champions confirmation still required before treating as verified.","requiresOfficialReview":true,"strictModeEligible":false},{"ability_id":"ABILITY_ANALYTIC","name":"Analytic","effect":"Boosts move power when the Pokémon moves last.","pokemon_count":2,"notes":"Imported from Pokemon_Abilities source","source":"https://www.serebii.net/pokedex-champions/","confidenceStatus":"Needs Champions Confirmation","confidenceReason":"Existing local data preserved; official Pokémon Champions confirmation still required before treating as verified.","requiresOfficialReview":true,"strictModeEligible":false},{"ability_id":"ABILITY_ANGER_POINT","name":"Anger Point","effect":"Raises Attack upon taking a critical hit.","pokemon_count":4,"notes":"Imported from Pokemon_Abilities source","source":"https://www.serebii.net/pokedex-champions/","confidenceStatus":"Needs Champions Confirmation","confidenceReason":"Existing local data preserved; official Pokémon Champions confirmation still required before treating as verified.","requiresOfficialReview":true,"strictModeEligible":false},{"ability_id":"ABILITY_ANTICIPATION","name":"Anticipation","effect":"Senses the foe’s dangerous moves.","pokemon_count":2,"notes":"Imported from Pokemon_Abilities source","source":"https://www.serebii.net/pokedex-champions/","confidenceStatus":"Needs Champions Confirmation","confidenceReason":"Existing local data preserved; official Pokémon Champions confirmation still required before treating as verified.","requiresOfficialReview":true,"strictModeEligible":false},{"ability_id":"ABILITY_ARMOR_TAIL","name":"Armor Tail","effect":"The mysterious tail covering the Pokémon's head makes opponents unable to use priority moves against the Pokémon or its allies.","pokemon_count":1,"notes":"Imported from Pokemon_Abilities source","source":"https://www.serebii.net/pokedex-champions/","confidenceStatus":"Needs Champions Confirmation","confidenceReason":"Existing local data preserved; official Pokémon Champions confirmation still required before treating as verified.","requiresOfficialReview":true,"strictModeEligible":false},{"ability_id":"ABILITY_AROMA_VEIL","name":"Aroma Veil","effect":"Protects allies from attacks that limit their move choices.","pokemon_count":2,"notes":"Imported from Pokemon_Abilities source","source":"https://www.serebii.net/pokedex-champions/","confidenceStatus":"Needs Champions Confirmation","confidenceReason":"Existing local data preserved; official Pokémon Champions confirmation still required before treating as verified.","requiresOfficialReview":true,"strictModeEligible":false},{"ability_id":"ABILITY_BERSERK","name":"Berserk","effect":"Boosts the Pokémon’s Sp. Atk stat when it takes a hit that causes its HP to become half or less.","pokemon_count":2,"notes":"Imported from Pokemon_Abilities source","source":"https://www.serebii.net/pokedex-champions/","confidenceStatus":"Needs Champions Confirmation","confidenceReason":"Existing local data preserved; official Pokémon Champions confirmation still required before treating as verified.","requiresOfficialReview":true,"strictModeEligible":false},{"ability_id":"ABILITY_BIG_PECKS","name":"Big Pecks","effect":"Protects the Pokémon from Defense-lowering attacks.","pokemon_count":1,"notes":"Imported from Pokemon_Abilities source","source":"https://www.serebii.net/pokedex-champions/","confidenceStatus":"Needs Champions Confirmation","confidenceReason":"Existing local data preserved; official Pokémon Champions confirmation still required before treating as verified.","requiresOfficialReview":true,"strictModeEligible":false},{"ability_id":"ABILITY_BLAZE","name":"Blaze","effect":"Ups FIRE moves in a pinch.","pokemon_count":8,"notes":"Imported from Pokemon_Abilities source","source":"https://www.serebii.net/pokedex-champions/","confidenceStatus":"Needs Champions Confirmation","confidenceReason":"Existing local data preserved; official Pokémon Champions confirmation still required before treating as verified.","requiresOfficialReview":true,"strictModeEligible":false},{"ability_id":"ABILITY_BULLETPROOF","name":"Bulletproof","effect":"Protects the Pokémon from some ball and bomb moves.","pokemon_count":3,"notes":"Imported from Pokemon_Abilities source","source":"https://www.serebii.net/pokedex-champions/","confidenceStatus":"Needs Champions Confirmation","confidenceReason":"Existing local data preserved; official Pokémon Champions confirmation still required before treating as verified.","requiresOfficialReview":true,"strictModeEligible":false},{"ability_id":"ABILITY_CHEEK_POUCH","name":"Cheek Pouch","effect":"Restores HP as well when the Pokémon eats a Berry.","pokemon_count":3,"notes":"Imported from Pokemon_Abilities source","source":"https://www.serebii.net/pokedex-champions/","confidenceStatus":"Needs Champions Confirmation","confidenceReason":"Existing local data preserved; official Pokémon Champions confirmation still required before treating as verified.","requiresOfficialReview":true,"strictModeEligible":false},{"ability_id":"ABILITY_CHLOROPHYLL","name":"Chlorophyll","effect":"Raises SPEED in sunshine.","pokemon_count":5,"notes":"Imported from Pokemon_Abilities source","source":"https://www.serebii.net/pokedex-champions/","confidenceStatus":"Needs Champions Confirmation","confidenceReason":"Existing local data preserved; official Pokémon Champions confirmation still required before treating as verified.","requiresOfficialReview":true,"strictModeEligible":false},{"ability_id":"ABILITY_CLEAR_BODY","name":"Clear Body","effect":"Prevents ability reduction.","pokemon_count":2,"notes":"Imported from Pokemon_Abilities source","source":"https://www.serebii.net/pokedex-champions/","confidenceStatus":"Needs Champions Confirmation","confidenceReason":"Existing local data preserved; official Pokémon Champions confirmation still required before treating as verified.","requiresOfficialReview":true,"strictModeEligible":false},{"ability_id":"ABILITY_CLOUD_NINE","name":"Cloud Nine","effect":"Negates weather effects.","pokemon_count":2,"notes":"Imported from Pokemon_Abilities source","source":"https://www.serebii.net/pokedex-champions/","confidenceStatus":"Needs Champions Confirmation","confidenceReason":"Existing local data preserved; official Pokémon Champions confirmation still required before treating as verified.","requiresOfficialReview":true,"strictModeEligible":false},{"ability_id":"ABILITY_COMPETITIVE","name":"Competitive","effect":"Boosts the Sp. Atk stat when a stat is lowered.","pokemon_count":1,"notes":"Imported from Pokemon_Abilities source","source":"https://www.serebii.net/pokedex-champions/","confidenceStatus":"Needs Champions Confirmation","confidenceReason":"Existing local data preserved; official Pokémon Champions confirmation still required before treating as verified.","requiresOfficialReview":true,"strictModeEligible":false},{"ability_id":"ABILITY_COMPOUND_EYES","name":"Compound Eyes","effect":"Raises accuracy.","pokemon_count":1,"notes":"Imported from Pokemon_Abilities source","source":"https://www.serebii.net/pokedex-champions/","confidenceStatus":"Needs Champions Confirmation","confidenceReason":"Existing local data preserved; official Pokémon Champions confirmation still required before treating as verified.","requiresOfficialReview":true,"strictModeEligible":false},{"ability_id":"ABILITY_CONTRARY","name":"Contrary","effect":"Makes stat changes have an opposite effect.","pokemon_count":1,"notes":"Imported from Pokemon_Abilities source","source":"https://www.serebii.net/pokedex-champions/","confidenceStatus":"Needs Champions Confirmation","confidenceReason":"Existing local data preserved; official Pokémon Champions confirmation still required before treating as verified.","requiresOfficialReview":true,"strictModeEligible":false},{"ability_id":"ABILITY_CORROSION","name":"Corrosion","effect":"The Pokémon can poison the target even if it’s a Steel or Poison type.","pokemon_count":2,"notes":"Imported from Pokemon_Abilities source","source":"https://www.serebii.net/pokedex-champions/","confidenceStatus":"Needs Champions Confirmation","confidenceReason":"Existing local data preserved; official Pokémon Champions confirmation still required before treating as verified.","requiresOfficialReview":true,"strictModeEligible":false},{"ability_id":"ABILITY_CUD_CHEW","name":"Cud Chew","effect":"When the Pokémon eats a Berry, it will regurgitate that Berry at the end of the next turn and eat it one more time.","pokemon_count":1,"notes":"Imported from Pokemon_Abilities source","source":"https://www.serebii.net/pokedex-champions/","confidenceStatus":"Needs Champions Confirmation","confidenceReason":"Existing local data preserved; official Pokémon Champions confirmation still required before treating as verified.","requiresOfficialReview":true,"strictModeEligible":false},{"ability_id":"ABILITY_CURSED_BODY","name":"Cursed Body","effect":"May disable a move used on the Pokémon.","pokemon_count":5,"notes":"Imported from Pokemon_Abilities source","source":"https://www.serebii.net/pokedex-champions/","confidenceStatus":"Needs Champions Confirmation","confidenceReason":"Existing local data preserved; official Pokémon Champions confirmation still required before treating as verified.","requiresOfficialReview":true,"strictModeEligible":false},{"ability_id":"ABILITY_CUTE_CHARM","name":"Cute Charm","effect":"Infatuates on contact.","pokemon_count":4,"notes":"Imported from Pokemon_Abilities source","source":"https://www.serebii.net/pokedex-champions/","confidenceStatus":"Needs Champions Confirmation","confidenceReason":"Existing local data preserved; official Pokémon Champions confirmation still required before treating as verified.","requiresOfficialReview":true,"strictModeEligible":false},{"ability_id":"ABILITY_DAMP","name":"Damp","effect":"Prevents self-destruction.","pokemon_count":2,"notes":"Imported from Pokemon_Abilities source","source":"https://www.serebii.net/pokedex-champions/","confidenceStatus":"Needs Champions Confirmation","confidenceReason":"Existing local data preserved; official Pokémon Champions confirmation still required before treating as verified.","requiresOfficialReview":true,"strictModeEligible":false},{"ability_id":"ABILITY_DEFIANT","name":"Defiant","effect":"When its stats are lowered its Attack increases.","pokemon_count":3,"notes":"Imported from Pokemon_Abilities source","source":"https://www.serebii.net/pokedex-champions/","confidenceStatus":"Needs Champions Confirmation","confidenceReason":"Existing local data preserved; official Pokémon Champions confirmation still required before treating as verified.","requiresOfficialReview":true,"strictModeEligible":false},{"ability_id":"ABILITY_DISGUISE","name":"Disguise","effect":"Once per battle, the shroud that covers the Pokémon can protect it from an attack.","pokemon_count":1,"notes":"Imported from Pokemon_Abilities source","source":"https://www.serebii.net/pokedex-champions/","confidenceStatus":"Needs Champions Confirmation","confidenceReason":"Existing local data preserved; official Pokémon Champions confirmation still required before treating as verified.","requiresOfficialReview":true,"strictModeEligible":false},{"ability_id":"ABILITY_DRAGONIZE","name":"Dragonize","effect":"The Pokémon's Normal-type moves become Dragon-type moves and their power is boosted by 20%.","pokemon_count":1,"notes":"Imported from Pokemon_Abilities source","source":"https://www.serebii.net/pokemonchampions/newabilities.shtml / https://game8.co/games/Pokemon-Champions/archives/590403","confidenceStatus":"Needs Champions Confirmation","confidenceReason":"Existing local data preserved; official Pokémon Champions confirmation still required before treating as verified.","requiresOfficialReview":true,"strictModeEligible":false},{"ability_id":"ABILITY_DRIZZLE","name":"Drizzle","effect":"Summons rain in battle.","pokemon_count":2,"notes":"Imported from Pokemon_Abilities source","source":"https://www.serebii.net/pokedex-champions/","confidenceStatus":"Needs Champions Confirmation","confidenceReason":"Existing local data preserved; official Pokémon Champions confirmation still required before treating as verified.","requiresOfficialReview":true,"strictModeEligible":false},{"ability_id":"ABILITY_DROUGHT","name":"Drought","effect":"Summons sunlight in battle.","pokemon_count":3,"notes":"Imported from Pokemon_Abilities source","source":"https://www.serebii.net/pokedex-champions/","confidenceStatus":"Needs Champions Confirmation","confidenceReason":"Existing local data preserved; official Pokémon Champions confirmation still required before treating as verified.","requiresOfficialReview":true,"strictModeEligible":false},{"ability_id":"ABILITY_DRY_SKIN","name":"Dry Skin","effect":"Reduces HP if it is hot. Water restores HP.","pokemon_count":2,"notes":"Imported from Pokemon_Abilities source","source":"https://www.serebii.net/pokedex-champions/","confidenceStatus":"Needs Champions Confirmation","confidenceReason":"Existing local data preserved; official Pokémon Champions confirmation still required before treating as verified.","requiresOfficialReview":true,"strictModeEligible":false},{"ability_id":"ABILITY_EARLY_BIRD","name":"Early Bird","effect":"Awakens quickly from sleep.","pokemon_count":2,"notes":"Imported from Pokemon_Abilities source","source":"https://www.serebii.net/pokedex-champions/","confidenceStatus":"Needs Champions Confirmation","confidenceReason":"Existing local data preserved; official Pokémon Champions confirmation still required before treating as verified.","requiresOfficialReview":true,"strictModeEligible":false},{"ability_id":"ABILITY_EARTH_EATER","name":"Earth Eater","effect":"If hit by a Ground-type move, the Pokémon has its HP restored instead of taking damage.","pokemon_count":1,"notes":"Imported from Pokemon_Abilities source","source":"https://www.serebii.net/pokedex-champions/","confidenceStatus":"Needs Champions Confirmation","confidenceReason":"Existing local data preserved; official Pokémon Champions confirmation still required before treating as verified.","requiresOfficialReview":true,"strictModeEligible":false},{"ability_id":"ABILITY_ELECTROMORPHOSIS","name":"Electromorphosis","effect":"The Pokémon becomes charged when it takes damage, boosting the power of the next Electric-type move the Pokémon uses.","pokemon_count":1,"notes":"Imported from Pokemon_Abilities source","source":"https://www.serebii.net/pokedex-champions/","confidenceStatus":"Needs Champions Confirmation","confidenceReason":"Existing local data preserved; official Pokémon Champions confirmation still required before treating as verified.","requiresOfficialReview":true,"strictModeEligible":false},{"ability_id":"ABILITY_FILTER","name":"Filter","effect":"Powers down super­ effective moves.","pokemon_count":1,"notes":"Imported from Pokemon_Abilities source","source":"https://www.serebii.net/pokedex-champions/","confidenceStatus":"Needs Champions Confirmation","confidenceReason":"Existing local data preserved; official Pokémon Champions confirmation still required before treating as verified.","requiresOfficialReview":true,"strictModeEligible":false},{"ability_id":"ABILITY_FLAME_BODY","name":"Flame Body","effect":"Burns the foe on contact.","pokemon_count":3,"notes":"Imported from Pokemon_Abilities source","source":"https://www.serebii.net/pokedex-champions/","confidenceStatus":"Needs Champions Confirmation","confidenceReason":"Existing local data preserved; official Pokémon Champions confirmation still required before treating as verified.","requiresOfficialReview":true,"strictModeEligible":false},{"ability_id":"ABILITY_FLASH_FIRE","name":"Flash Fire","effect":"Powers up if hit by fire.","pokemon_count":8,"notes":"Imported from Pokemon_Abilities source","source":"https://www.serebii.net/pokedex-champions/","confidenceStatus":"Needs Champions Confirmation","confidenceReason":"Existing local data preserved; official Pokémon Champions confirmation still required before treating as verified.","requiresOfficialReview":true,"strictModeEligible":false},{"ability_id":"ABILITY_FLOWER_VEIL","name":"Flower Veil","effect":"Prevents lowering of ally Grass-type Pokémon’s stats.","pokemon_count":2,"notes":"Imported from Pokemon_Abilities source","source":"https://www.serebii.net/pokedex-champions/","confidenceStatus":"Needs Champions Confirmation","confidenceReason":"Existing local data preserved; official Pokémon Champions confirmation still required before treating as verified.","requiresOfficialReview":true,"strictModeEligible":false},{"ability_id":"ABILITY_FORECAST","name":"Forecast","effect":"Changes with the weather.","pokemon_count":1,"notes":"Imported from Pokemon_Abilities source","source":"https://www.serebii.net/pokedex-champions/","confidenceStatus":"Needs Champions Confirmation","confidenceReason":"Existing local data preserved; official Pokémon Champions confirmation still required before treating as verified.","requiresOfficialReview":true,"strictModeEligible":false},{"ability_id":"ABILITY_FRIEND_GUARD","name":"Friend Guard","effect":"Reduces damage done to allies.","pokemon_count":2,"notes":"Imported from Pokemon_Abilities source","source":"https://www.serebii.net/pokedex-champions/","confidenceStatus":"Needs Champions Confirmation","confidenceReason":"Existing local data preserved; official Pokémon Champions confirmation still required before treating as verified.","requiresOfficialReview":true,"strictModeEligible":false},{"ability_id":"ABILITY_FRISK","name":"Frisk","effect":"The Pokémon can check the foe’s held item.","pokemon_count":5,"notes":"Imported from Pokemon_Abilities source","source":"https://www.serebii.net/pokedex-champions/","confidenceStatus":"Needs Champions Confirmation","confidenceReason":"Existing local data preserved; official Pokémon Champions confirmation still required before treating as verified.","requiresOfficialReview":true,"strictModeEligible":false},{"ability_id":"ABILITY_FUR_COAT","name":"Fur Coat","effect":"Halves damage from physical moves.","pokemon_count":1,"notes":"Imported from Pokemon_Abilities source","source":"https://www.serebii.net/pokedex-champions/","confidenceStatus":"Needs Champions Confirmation","confidenceReason":"Existing local data preserved; official Pokémon Champions confirmation still required before treating as verified.","requiresOfficialReview":true,"strictModeEligible":false},{"ability_id":"ABILITY_GALE_WINGS","name":"Gale Wings","effect":"Gives priority to Flying-type moves.","pokemon_count":1,"notes":"Imported from Pokemon_Abilities source","source":"https://www.serebii.net/pokedex-champions/","confidenceStatus":"Needs Champions Confirmation","confidenceReason":"Existing local data preserved; official Pokémon Champions confirmation still required before treating as verified.","requiresOfficialReview":true,"strictModeEligible":false},{"ability_id":"ABILITY_GLUTTONY","name":"Gluttony","effect":"Encourages the early use of a held Berry.","pokemon_count":7,"notes":"Imported from Pokemon_Abilities source","source":"https://www.serebii.net/pokedex-champions/","confidenceStatus":"Needs Champions Confirmation","confidenceReason":"Existing local data preserved; official Pokémon Champions confirmation still required before treating as verified.","requiresOfficialReview":true,"strictModeEligible":false},{"ability_id":"ABILITY_GOOEY","name":"Gooey","effect":"Contact with the Pokémon lowers the attacker’s Speed stat.","pokemon_count":1,"notes":"Imported from Pokemon_Abilities source","source":"https://www.serebii.net/pokedex-champions/","confidenceStatus":"Needs Champions Confirmation","confidenceReason":"Existing local data preserved; official Pokémon Champions confirmation still required before treating as verified.","requiresOfficialReview":true,"strictModeEligible":false},{"ability_id":"ABILITY_GUTS","name":"Guts","effect":"Ups ATTACK if suffering.","pokemon_count":5,"notes":"Imported from Pokemon_Abilities source","source":"https://www.serebii.net/pokedex-champions/","confidenceStatus":"Needs Champions Confirmation","confidenceReason":"Existing local data preserved; official Pokémon Champions confirmation still required before treating as verified.","requiresOfficialReview":true,"strictModeEligible":false},{"ability_id":"ABILITY_HARVEST","name":"Harvest","effect":"May create another Berry after one is used.","pokemon_count":1,"notes":"Imported from Pokemon_Abilities source","source":"https://www.serebii.net/pokedex-champions/","confidenceStatus":"Needs Champions Confirmation","confidenceReason":"Existing local data preserved; official Pokémon Champions confirmation still required before treating as verified.","requiresOfficialReview":true,"strictModeEligible":false},{"ability_id":"ABILITY_HEALER","name":"Healer","effect":"May heal an ally’s status conditions.","pokemon_count":4,"notes":"Imported from Pokemon_Abilities source","source":"https://www.serebii.net/pokedex-champions/","confidenceStatus":"Needs Champions Confirmation","confidenceReason":"Existing local data preserved; official Pokémon Champions confirmation still required before treating as verified.","requiresOfficialReview":true,"strictModeEligible":false},{"ability_id":"ABILITY_HEATPROOF","name":"Heatproof","effect":"Weakens the power of Fire-type moves.","pokemon_count":1,"notes":"Imported from Pokemon_Abilities source","source":"https://www.serebii.net/pokedex-champions/","confidenceStatus":"Needs Champions Confirmation","confidenceReason":"Existing local data preserved; official Pokémon Champions confirmation still required before treating as verified.","requiresOfficialReview":true,"strictModeEligible":false},{"ability_id":"ABILITY_HEAVY_METAL","name":"Heavy Metal","effect":"Doubles the Pokémon’s weight.","pokemon_count":1,"notes":"Imported from Pokemon_Abilities source","source":"https://www.serebii.net/pokedex-champions/","confidenceStatus":"Needs Champions Confirmation","confidenceReason":"Existing local data preserved; official Pokémon Champions confirmation still required before treating as verified.","requiresOfficialReview":true,"strictModeEligible":false},{"ability_id":"ABILITY_HOSPITALITY","name":"Hospitality","effect":"When the Pokémon enters a battle, it showers its ally with hospitality, restoring a small amount of the ally's HP","pokemon_count":1,"notes":"Imported from Pokemon_Abilities source","source":"https://www.serebii.net/pokedex-champions/","confidenceStatus":"Needs Champions Confirmation","confidenceReason":"Existing local data preserved; official Pokémon Champions confirmation still required before treating as verified.","requiresOfficialReview":true,"strictModeEligible":false},{"ability_id":"ABILITY_HUGE_POWER","name":"Huge Power","effect":"Raises ATTACK.","pokemon_count":3,"notes":"Imported from Pokemon_Abilities source","source":"https://www.serebii.net/pokedex-champions/","confidenceStatus":"Needs Champions Confirmation","confidenceReason":"Existing local data preserved; official Pokémon Champions confirmation still required before treating as verified.","requiresOfficialReview":true,"strictModeEligible":false},{"ability_id":"ABILITY_HUNGER_SWITCH","name":"Hunger Switch","effect":"The Pokémon changes its form, alternating between its Full Belly Mode and Hangry Mode after the end of each turn.","pokemon_count":1,"notes":"Imported from Pokemon_Abilities source","source":"https://www.serebii.net/pokedex-champions/","confidenceStatus":"Needs Champions Confirmation","confidenceReason":"Existing local data preserved; official Pokémon Champions confirmation still required before treating as verified.","requiresOfficialReview":true,"strictModeEligible":false},{"ability_id":"ABILITY_HUSTLE","name":"Hustle","effect":"Trades accuracy for power.","pokemon_count":1,"notes":"Imported from Pokemon_Abilities source","source":"https://www.serebii.net/pokedex-champions/","confidenceStatus":"Needs Champions Confirmation","confidenceReason":"Existing local data preserved; official Pokémon Champions confirmation still required before treating as verified.","requiresOfficialReview":true,"strictModeEligible":false},{"ability_id":"ABILITY_HYDRATION","name":"Hydration","effect":"Heals status problems if it is raining.","pokemon_count":2,"notes":"Imported from Pokemon_Abilities source","source":"https://www.serebii.net/pokedex-champions/","confidenceStatus":"Needs Champions Confirmation","confidenceReason":"Existing local data preserved; official Pokémon Champions confirmation still required before treating as verified.","requiresOfficialReview":true,"strictModeEligible":false},{"ability_id":"ABILITY_HYPER_CUTTER","name":"Hyper Cutter","effect":"Prevents ATTACK reduction.","pokemon_count":3,"notes":"Imported from Pokemon_Abilities source","source":"https://www.serebii.net/pokedex-champions/","confidenceStatus":"Needs Champions Confirmation","confidenceReason":"Existing local data preserved; official Pokémon Champions confirmation still required before treating as verified.","requiresOfficialReview":true,"strictModeEligible":false},{"ability_id":"ABILITY_ICE_BODY","name":"Ice Body","effect":"The Pokémon regains HP in a hailstorm.","pokemon_count":4,"notes":"Imported from Pokemon_Abilities source","source":"https://www.serebii.net/pokedex-champions/","confidenceStatus":"Needs Champions Confirmation","confidenceReason":"Existing local data preserved; official Pokémon Champions confirmation still required before treating as verified.","requiresOfficialReview":true,"strictModeEligible":false},{"ability_id":"ABILITY_ILLUMINATE","name":"Illuminate","effect":"Encounter rate increases.","pokemon_count":2,"notes":"Imported from Pokemon_Abilities source","source":"https://www.serebii.net/pokedex-champions/","confidenceStatus":"Needs Champions Confirmation","confidenceReason":"Existing local data preserved; official Pokémon Champions confirmation still required before treating as verified.","requiresOfficialReview":true,"strictModeEligible":false},{"ability_id":"ABILITY_ILLUSION","name":"Illusion","effect":"Comes out disguised as the Pokémon in back.","pokemon_count":1,"notes":"Imported from Pokemon_Abilities source","source":"https://www.serebii.net/pokedex-champions/","confidenceStatus":"Needs Champions Confirmation","confidenceReason":"Existing local data preserved; official Pokémon Champions confirmation still required before treating as verified.","requiresOfficialReview":true,"strictModeEligible":false},{"ability_id":"ABILITY_IMMUNITY","name":"Immunity","effect":"Prevents poisoning.","pokemon_count":1,"notes":"Imported from Pokemon_Abilities source","source":"https://www.serebii.net/pokedex-champions/","confidenceStatus":"Needs Champions Confirmation","confidenceReason":"Existing local data preserved; official Pokémon Champions confirmation still required before treating as verified.","requiresOfficialReview":true,"strictModeEligible":false},{"ability_id":"ABILITY_IMPOSTER","name":"Imposter","effect":"It transforms itself into the Pokémon it is facing.","pokemon_count":1,"notes":"Imported from Pokemon_Abilities source","source":"https://www.serebii.net/pokedex-champions/","confidenceStatus":"Needs Champions Confirmation","confidenceReason":"Existing local data preserved; official Pokémon Champions confirmation still required before treating as verified.","requiresOfficialReview":true,"strictModeEligible":false},{"ability_id":"ABILITY_INFILTRATOR","name":"Infiltrator","effect":"Passes through the foe’s barrier and strikes.","pokemon_count":6,"notes":"Imported from Pokemon_Abilities source","source":"https://www.serebii.net/pokedex-champions/","confidenceStatus":"Needs Champions Confirmation","confidenceReason":"Existing local data preserved; official Pokémon Champions confirmation still required before treating as verified.","requiresOfficialReview":true,"strictModeEligible":false},{"ability_id":"ABILITY_INNARDS_OUT","name":"Innards Out","effect":"Damages the attacker landing the finishing hit by the amount equal to its last HP.","pokemon_count":1,"notes":"Imported from Pokemon_Abilities source","source":"https://www.serebii.net/pokedex-champions/","confidenceStatus":"Needs Champions Confirmation","confidenceReason":"Existing local data preserved; official Pokémon Champions confirmation still required before treating as verified.","requiresOfficialReview":true,"strictModeEligible":false},{"ability_id":"ABILITY_INNER_FOCUS","name":"Inner Focus","effect":"Prevents flinching.","pokemon_count":9,"notes":"Imported from Pokemon_Abilities source","source":"https://www.serebii.net/pokedex-champions/","confidenceStatus":"Needs Champions Confirmation","confidenceReason":"Existing local data preserved; official Pokémon Champions confirmation still required before treating as verified.","requiresOfficialReview":true,"strictModeEligible":false},{"ability_id":"ABILITY_INSOMNIA","name":"Insomnia","effect":"Prevents sleep.","pokemon_count":3,"notes":"Imported from Pokemon_Abilities source","source":"https://www.serebii.net/pokedex-champions/","confidenceStatus":"Needs Champions Confirmation","confidenceReason":"Existing local data preserved; official Pokémon Champions confirmation still required before treating as verified.","requiresOfficialReview":true,"strictModeEligible":false},{"ability_id":"ABILITY_INTIMIDATE","name":"Intimidate","effect":"Lowers the foe’s ATTACK.","pokemon_count":9,"notes":"Imported from Pokemon_Abilities source","source":"https://www.serebii.net/pokedex-champions/","confidenceStatus":"Needs Champions Confirmation","confidenceReason":"Existing local data preserved; official Pokémon Champions confirmation still required before treating as verified.","requiresOfficialReview":true,"strictModeEligible":false},{"ability_id":"ABILITY_IRON_FIST","name":"Iron Fist","effect":"Boosts the power of punching moves.","pokemon_count":6,"notes":"Imported from Pokemon_Abilities source","source":"https://www.serebii.net/pokedex-champions/","confidenceStatus":"Needs Champions Confirmation","confidenceReason":"Existing local data preserved; official Pokémon Champions confirmation still required before treating as verified.","requiresOfficialReview":true,"strictModeEligible":false},{"ability_id":"ABILITY_JUSTIFIED","name":"Justified","effect":"Raises Attack when hit by a Dark-type move.","pokemon_count":4,"notes":"Imported from Pokemon_Abilities source","source":"https://www.serebii.net/pokedex-champions/","confidenceStatus":"Needs Champions Confirmation","confidenceReason":"Existing local data preserved; official Pokémon Champions confirmation still required before treating as verified.","requiresOfficialReview":true,"strictModeEligible":false},{"ability_id":"ABILITY_KEEN_EYE","name":"Keen Eye","effect":"Prevents loss of accuracy.","pokemon_count":6,"notes":"Imported from Pokemon_Abilities source","source":"https://www.serebii.net/pokedex-champions/","confidenceStatus":"Needs Champions Confirmation","confidenceReason":"Existing local data preserved; official Pokémon Champions confirmation still required before treating as verified.","requiresOfficialReview":true,"strictModeEligible":false},{"ability_id":"ABILITY_KLUTZ","name":"Klutz","effect":"The Pokémon can’t use any held items.","pokemon_count":3,"notes":"Imported from Pokemon_Abilities source","source":"https://www.serebii.net/pokedex-champions/","confidenceStatus":"Needs Champions Confirmation","confidenceReason":"Existing local data preserved; official Pokémon Champions confirmation still required before treating as verified.","requiresOfficialReview":true,"strictModeEligible":false},{"ability_id":"ABILITY_LEAF_GUARD","name":"Leaf Guard","effect":"Prevents status problems in sunny weather.","pokemon_count":3,"notes":"Imported from Pokemon_Abilities source","source":"https://www.serebii.net/pokedex-champions/","confidenceStatus":"Needs Champions Confirmation","confidenceReason":"Existing local data preserved; official Pokémon Champions confirmation still required before treating as verified.","requiresOfficialReview":true,"strictModeEligible":false},{"ability_id":"ABILITY_LEVITATE","name":"Levitate","effect":"Gives full immunity to all Ground-type moves.","pokemon_count":10,"notes":"Imported from Pokemon_Abilities source","source":"https://www.serebii.net/pokedex-champions/","confidenceStatus":"Needs Champions Confirmation","confidenceReason":"Existing local data preserved; official Pokémon Champions confirmation still required before treating as verified.","requiresOfficialReview":true,"strictModeEligible":false},{"ability_id":"ABILITY_LIGHT_METAL","name":"Light Metal","effect":"Halves the Pokémon’s weight.","pokemon_count":1,"notes":"Imported from Pokemon_Abilities source","source":"https://www.serebii.net/pokedex-champions/","confidenceStatus":"Needs Champions Confirmation","confidenceReason":"Existing local data preserved; official Pokémon Champions confirmation still required before treating as verified.","requiresOfficialReview":true,"strictModeEligible":false},{"ability_id":"ABILITY_LIGHTNING_ROD","name":"Lightning Rod","effect":"Draws electrical moves.","pokemon_count":4,"notes":"Imported from Pokemon_Abilities source","source":"https://www.serebii.net/pokedex-champions/","confidenceStatus":"Needs Champions Confirmation","confidenceReason":"Existing local data preserved; official Pokémon Champions confirmation still required before treating as verified.","requiresOfficialReview":true,"strictModeEligible":false},{"ability_id":"ABILITY_LIMBER","name":"Limber","effect":"Prevents paralysis.","pokemon_count":6,"notes":"Imported from Pokemon_Abilities source","source":"https://www.serebii.net/pokedex-champions/","confidenceStatus":"Needs Champions Confirmation","confidenceReason":"Existing local data preserved; official Pokémon Champions confirmation still required before treating as verified.","requiresOfficialReview":true,"strictModeEligible":false},{"ability_id":"ABILITY_LIQUID_VOICE","name":"Liquid Voice","effect":"All sound-based moves become Water-type moves.","pokemon_count":1,"notes":"Imported from Pokemon_Abilities source","source":"https://www.serebii.net/pokedex-champions/","confidenceStatus":"Needs Champions Confirmation","confidenceReason":"Existing local data preserved; official Pokémon Champions confirmation still required before treating as verified.","requiresOfficialReview":true,"strictModeEligible":false},{"ability_id":"ABILITY_LONG_REACH","name":"Long Reach","effect":"The Pokémon uses its moves without making contact with the target.","pokemon_count":1,"notes":"Imported from Pokemon_Abilities source","source":"https://www.serebii.net/pokedex-champions/","confidenceStatus":"Needs Champions Confirmation","confidenceReason":"Existing local data preserved; official Pokémon Champions confirmation still required before treating as verified.","requiresOfficialReview":true,"strictModeEligible":false},{"ability_id":"ABILITY_MAGIC_BOUNCE","name":"Magic Bounce","effect":"Reflects status- changing moves.","pokemon_count":5,"notes":"Imported from Pokemon_Abilities source","source":"https://www.serebii.net/pokedex-champions/","confidenceStatus":"Needs Champions Confirmation","confidenceReason":"Existing local data preserved; official Pokémon Champions confirmation still required before treating as verified.","requiresOfficialReview":true,"strictModeEligible":false},{"ability_id":"ABILITY_MAGIC_GUARD","name":"Magic Guard","effect":"The Pokémon only takes damage from attacks.","pokemon_count":3,"notes":"Imported from Pokemon_Abilities source","source":"https://www.serebii.net/pokedex-champions/","confidenceStatus":"Needs Champions Confirmation","confidenceReason":"Existing local data preserved; official Pokémon Champions confirmation still required before treating as verified.","requiresOfficialReview":true,"strictModeEligible":false},{"ability_id":"ABILITY_MAGICIAN","name":"Magician","effect":"The Pokémon steals the held item of a Pokémon it hits with a move.","pokemon_count":2,"notes":"Imported from Pokemon_Abilities source","source":"https://www.serebii.net/pokedex-champions/","confidenceStatus":"Needs Champions Confirmation","confidenceReason":"Existing local data preserved; official Pokémon Champions confirmation still required before treating as verified.","requiresOfficialReview":true,"strictModeEligible":false},{"ability_id":"ABILITY_MAGMA_ARMOR","name":"Magma Armor","effect":"Prevents freezing.","pokemon_count":1,"notes":"Imported from Pokemon_Abilities source","source":"https://www.serebii.net/pokedex-champions/","confidenceStatus":"Needs Champions Confirmation","confidenceReason":"Existing local data preserved; official Pokémon Champions confirmation still required before treating as verified.","requiresOfficialReview":true,"strictModeEligible":false},{"ability_id":"ABILITY_MARVEL_SCALE","name":"Marvel Scale","effect":"Ups DEFENSE if suffering.","pokemon_count":1,"notes":"Imported from Pokemon_Abilities source","source":"https://www.serebii.net/pokedex-champions/","confidenceStatus":"Needs Champions Confirmation","confidenceReason":"Existing local data preserved; official Pokémon Champions confirmation still required before treating as verified.","requiresOfficialReview":true,"strictModeEligible":false},{"ability_id":"ABILITY_MEGA_LAUNCHER","name":"Mega Launcher","effect":"Powers up aura and pulse moves.","pokemon_count":2,"notes":"Imported from Pokemon_Abilities source","source":"https://www.serebii.net/pokedex-champions/","confidenceStatus":"Needs Champions Confirmation","confidenceReason":"Existing local data preserved; official Pokémon Champions confirmation still required before treating as verified.","requiresOfficialReview":true,"strictModeEligible":false},{"ability_id":"ABILITY_MEGA_SOL","name":"Mega Sol","effect":"Even when the sunlight has not turned harsh, the Pokémon can use its moves as if the weather were harsh sunlight.","pokemon_count":2,"notes":"Imported from Pokemon_Abilities source","source":"https://www.serebii.net/pokemonchampions/newabilities.shtml / https://game8.co/games/Pokemon-Champions/archives/590403","confidenceStatus":"Needs Champions Confirmation","confidenceReason":"Existing local data preserved; official Pokémon Champions confirmation still required before treating as verified.","requiresOfficialReview":true,"strictModeEligible":false},{"ability_id":"ABILITY_MERCILESS","name":"Merciless","effect":"The Pokémon’s attacks become critical hits if the target is poisoned.","pokemon_count":1,"notes":"Imported from Pokemon_Abilities source","source":"https://www.serebii.net/pokedex-champions/","confidenceStatus":"Needs Champions Confirmation","confidenceReason":"Existing local data preserved; official Pokémon Champions confirmation still required before treating as verified.","requiresOfficialReview":true,"strictModeEligible":false},{"ability_id":"ABILITY_MINUS","name":"Minus","effect":"Powers up with PLUS.","pokemon_count":1,"notes":"Imported from Pokemon_Abilities source","source":"https://www.serebii.net/pokedex-champions/","confidenceStatus":"Needs Champions Confirmation","confidenceReason":"Existing local data preserved; official Pokémon Champions confirmation still required before treating as verified.","requiresOfficialReview":true,"strictModeEligible":false},{"ability_id":"ABILITY_MIRROR_ARMOR","name":"Mirror Armor","effect":"Bounces back only the stat-lowering effects that the Pokémon receives.","pokemon_count":1,"notes":"Imported from Pokemon_Abilities source","source":"https://www.serebii.net/pokedex-champions/","confidenceStatus":"Needs Champions Confirmation","confidenceReason":"Existing local data preserved; official Pokémon Champions confirmation still required before treating as verified.","requiresOfficialReview":true,"strictModeEligible":false},{"ability_id":"ABILITY_MOLD_BREAKER","name":"Mold damage pressure","effect":"Moves can be used regardless of abilities.","pokemon_count":10,"notes":"Imported from Pokemon_Abilities source","source":"https://www.serebii.net/pokedex-champions/","confidenceStatus":"Needs Champions Confirmation","confidenceReason":"Existing local data preserved; official Pokémon Champions confirmation still required before treating as verified.","requiresOfficialReview":true,"strictModeEligible":false},{"ability_id":"ABILITY_MOODY","name":"Moody","effect":"Raises one stat and lowers another.","pokemon_count":2,"notes":"Imported from Pokemon_Abilities source","source":"https://www.serebii.net/pokedex-champions/","confidenceStatus":"Needs Champions Confirmation","confidenceReason":"Existing local data preserved; official Pokémon Champions confirmation still required before treating as verified.","requiresOfficialReview":true,"strictModeEligible":false},{"ability_id":"ABILITY_MOTOR_DRIVE","name":"Motor Drive","effect":"Raises Speed if hit by an Electric-type move.","pokemon_count":1,"notes":"Imported from Pokemon_Abilities source","source":"https://www.serebii.net/pokedex-champions/","confidenceStatus":"Needs Champions Confirmation","confidenceReason":"Existing local data preserved; official Pokémon Champions confirmation still required before treating as verified.","requiresOfficialReview":true,"strictModeEligible":false},{"ability_id":"ABILITY_MOXIE","name":"Moxie","effect":"Boosts Attack after knocking out any Pokémon.","pokemon_count":5,"notes":"Imported from Pokemon_Abilities source","source":"https://www.serebii.net/pokedex-champions/","confidenceStatus":"Needs Champions Confirmation","confidenceReason":"Existing local data preserved; official Pokémon Champions confirmation still required before treating as verified.","requiresOfficialReview":true,"strictModeEligible":false},{"ability_id":"ABILITY_MULTISCALE","name":"Multiscale","effect":"Reduces damage when HP is full.","pokemon_count":1,"notes":"Imported from Pokemon_Abilities source","source":"https://www.serebii.net/pokedex-champions/","confidenceStatus":"Needs Champions Confirmation","confidenceReason":"Existing local data preserved; official Pokémon Champions confirmation still required before treating as verified.","requiresOfficialReview":true,"strictModeEligible":false},{"ability_id":"ABILITY_MUMMY","name":"Mummy","effect":"Contact with this Pokémon spreads this Ability.","pokemon_count":1,"notes":"Imported from Pokemon_Abilities source","source":"https://www.serebii.net/pokedex-champions/","confidenceStatus":"Needs Champions Confirmation","confidenceReason":"Existing local data preserved; official Pokémon Champions confirmation still required before treating as verified.","requiresOfficialReview":true,"strictModeEligible":false},{"ability_id":"ABILITY_NATURAL_CURE","name":"Natural Cure","effect":"Heals upon switching out.","pokemon_count":4,"notes":"Imported from Pokemon_Abilities source","source":"https://www.serebii.net/pokedex-champions/","confidenceStatus":"Needs Champions Confirmation","confidenceReason":"Existing local data preserved; official Pokémon Champions confirmation still required before treating as verified.","requiresOfficialReview":true,"strictModeEligible":false},{"ability_id":"ABILITY_NO_GUARD","name":"No Guard","effect":"Ensures the Pokémon and its foe’s attacks land.","pokemon_count":4,"notes":"Imported from Pokemon_Abilities source","source":"https://www.serebii.net/pokedex-champions/","confidenceStatus":"Needs Champions Confirmation","confidenceReason":"Existing local data preserved; official Pokémon Champions confirmation still required before treating as verified.","requiresOfficialReview":true,"strictModeEligible":false},{"ability_id":"ABILITY_OBLIVIOUS","name":"Oblivious","effect":"Prevents attraction.","pokemon_count":4,"notes":"Imported from Pokemon_Abilities source","source":"https://www.serebii.net/pokedex-champions/","confidenceStatus":"Needs Champions Confirmation","confidenceReason":"Existing local data preserved; official Pokémon Champions confirmation still required before treating as verified.","requiresOfficialReview":true,"strictModeEligible":false},{"ability_id":"ABILITY_OPPORTUNIST","name":"Opportunist","effect":"If an opponent's stat is boosted, the Pokémon seizes the opportunity to boost the same stat for itself.","pokemon_count":1,"notes":"Imported from Pokemon_Abilities source","source":"https://www.serebii.net/pokedex-champions/","confidenceStatus":"Needs Champions Confirmation","confidenceReason":"Existing local data preserved; official Pokémon Champions confirmation still required before treating as verified.","requiresOfficialReview":true,"strictModeEligible":false},{"ability_id":"ABILITY_OVERCOAT","name":"Overcoat","effect":"Protects the Pokémon from damage from weather.","pokemon_count":3,"notes":"Imported from Pokemon_Abilities source","source":"https://www.serebii.net/pokedex-champions/","confidenceStatus":"Needs Champions Confirmation","confidenceReason":"Existing local data preserved; official Pokémon Champions confirmation still required before treating as verified.","requiresOfficialReview":true,"strictModeEligible":false},{"ability_id":"ABILITY_OVERGROW","name":"Overgrow","effect":"Powers up Grass-type moves in a pinch.","pokemon_count":8,"notes":"Imported from Pokemon_Abilities source","source":"https://www.serebii.net/pokedex-champions/","confidenceStatus":"Needs Champions Confirmation","confidenceReason":"Existing local data preserved; official Pokémon Champions confirmation still required before treating as verified.","requiresOfficialReview":true,"strictModeEligible":false},{"ability_id":"ABILITY_OWN_TEMPO","name":"Own Tempo","effect":"Prevents confusion.","pokemon_count":5,"notes":"Imported from Pokemon_Abilities source","source":"https://www.serebii.net/pokedex-champions/","confidenceStatus":"Needs Champions Confirmation","confidenceReason":"Existing local data preserved; official Pokémon Champions confirmation still required before treating as verified.","requiresOfficialReview":true,"strictModeEligible":false},{"ability_id":"ABILITY_PARENTAL_BOND","name":"Parental Bond","effect":"Parent and child attack together.","pokemon_count":1,"notes":"Imported from Pokemon_Abilities source","source":"https://www.serebii.net/pokedex-champions/","confidenceStatus":"Needs Champions Confirmation","confidenceReason":"Existing local data preserved; official Pokémon Champions confirmation still required before treating as verified.","requiresOfficialReview":true,"strictModeEligible":false},{"ability_id":"ABILITY_PICKPOCKET","name":"Pickpocket","effect":"Steals an item when hit by another Pokémon.","pokemon_count":2,"notes":"Imported from Pokemon_Abilities source","source":"https://www.serebii.net/pokedex-champions/","confidenceStatus":"Needs Champions Confirmation","confidenceReason":"Existing local data preserved; official Pokémon Champions confirmation still required before treating as verified.","requiresOfficialReview":true,"strictModeEligible":false},{"ability_id":"ABILITY_PICKUP","name":"Pickup","effect":"May pick up items.","pokemon_count":2,"notes":"Imported from Pokemon_Abilities source","source":"https://www.serebii.net/pokedex-champions/","confidenceStatus":"Needs Champions Confirmation","confidenceReason":"Existing local data preserved; official Pokémon Champions confirmation still required before treating as verified.","requiresOfficialReview":true,"strictModeEligible":false},{"ability_id":"ABILITY_PIERCING_DRILL","name":"Piercing Drill","effect":"When the Pokémon uses contact moves, it can hit even targets that are protecting themselves, dealing 1/4 of the damage that the move would otherwise deal. Everything aside from the target's protective effects is still triggered.","pokemon_count":1,"notes":"Imported from Pokemon_Abilities source","source":"https://www.serebii.net/pokemonchampions/newabilities.shtml / https://game8.co/games/Pokemon-Champions/archives/590403","confidenceStatus":"Needs Champions Confirmation","confidenceReason":"Existing local data preserved; official Pokémon Champions confirmation still required before treating as verified.","requiresOfficialReview":true,"strictModeEligible":false},{"ability_id":"ABILITY_PIXILATE","name":"Pixilate","effect":"Normal-type moves become Fairy-type moves.","pokemon_count":3,"notes":"Imported from Pokemon_Abilities source","source":"https://www.serebii.net/pokedex-champions/","confidenceStatus":"Needs Champions Confirmation","confidenceReason":"Existing local data preserved; official Pokémon Champions confirmation still required before treating as verified.","requiresOfficialReview":true,"strictModeEligible":false},{"ability_id":"ABILITY_PLUS","name":"Plus","effect":"Powers up with MINUS.","pokemon_count":2,"notes":"Imported from Pokemon_Abilities source","source":"https://www.serebii.net/pokedex-champions/","confidenceStatus":"Needs Champions Confirmation","confidenceReason":"Existing local data preserved; official Pokémon Champions confirmation still required before treating as verified.","requiresOfficialReview":true,"strictModeEligible":false},{"ability_id":"ABILITY_POISON_HEAL","name":"Poison Heal","effect":"Restores HP if the Pokémon is poisoned.","pokemon_count":1,"notes":"Imported from Pokemon_Abilities source","source":"https://www.serebii.net/pokedex-champions/","confidenceStatus":"Needs Champions Confirmation","confidenceReason":"Existing local data preserved; official Pokémon Champions confirmation still required before treating as verified.","requiresOfficialReview":true,"strictModeEligible":false},{"ability_id":"ABILITY_POISON_POINT","name":"Poison Point","effect":"Poisons foe on contact.","pokemon_count":1,"notes":"Imported from Pokemon_Abilities source","source":"https://www.serebii.net/pokedex-champions/","confidenceStatus":"Needs Champions Confirmation","confidenceReason":"Existing local data preserved; official Pokémon Champions confirmation still required before treating as verified.","requiresOfficialReview":true,"strictModeEligible":false},{"ability_id":"ABILITY_POISON_TOUCH","name":"Poison Touch","effect":"May poison targets when a Pokémon makes contact.","pokemon_count":2,"notes":"Imported from Pokemon_Abilities source","source":"https://www.serebii.net/pokedex-champions/","confidenceStatus":"Needs Champions Confirmation","confidenceReason":"Existing local data preserved; official Pokémon Champions confirmation still required before treating as verified.","requiresOfficialReview":true,"strictModeEligible":false},{"ability_id":"ABILITY_PRANKSTER","name":"Prankster","effect":"Gives priority to a status move.","pokemon_count":5,"notes":"Imported from Pokemon_Abilities source","source":"https://www.serebii.net/pokedex-champions/","confidenceStatus":"Needs Champions Confirmation","confidenceReason":"Existing local data preserved; official Pokémon Champions confirmation still required before treating as verified.","requiresOfficialReview":true,"strictModeEligible":false},{"ability_id":"ABILITY_PRESSURE","name":"Pressure","effect":"Raises foe’s PP usage.","pokemon_count":7,"notes":"Imported from Pokemon_Abilities source","source":"https://www.serebii.net/pokedex-champions/","confidenceStatus":"Needs Champions Confirmation","confidenceReason":"Existing local data preserved; official Pokémon Champions confirmation still required before treating as verified.","requiresOfficialReview":true,"strictModeEligible":false},{"ability_id":"ABILITY_PROTEAN","name":"Protean","effect":"Changes the Pokémon’s type to the type of the move it’s using.","pokemon_count":3,"notes":"Imported from Pokemon_Abilities source","source":"https://www.serebii.net/pokedex-champions/","confidenceStatus":"Needs Champions Confirmation","confidenceReason":"Existing local data preserved; official Pokémon Champions confirmation still required before treating as verified.","requiresOfficialReview":true,"strictModeEligible":false},{"ability_id":"ABILITY_PURE_POWER","name":"Pure Power","effect":"Raises ATTACK.","pokemon_count":2,"notes":"Imported from Pokemon_Abilities source","source":"https://www.serebii.net/pokedex-champions/","confidenceStatus":"Needs Champions Confirmation","confidenceReason":"Existing local data preserved; official Pokémon Champions confirmation still required before treating as verified.","requiresOfficialReview":true,"strictModeEligible":false},{"ability_id":"ABILITY_PURIFYING_SALT","name":"Purifying Salt","effect":"The Pokémon's pure salt protects it from status conditions and halves the damage taken from Ghost-type moves.","pokemon_count":1,"notes":"Imported from Pokemon_Abilities source","source":"https://www.serebii.net/pokedex-champions/","confidenceStatus":"Needs Champions Confirmation","confidenceReason":"Existing local data preserved; official Pokémon Champions confirmation still required before treating as verified.","requiresOfficialReview":true,"strictModeEligible":false},{"ability_id":"ABILITY_QUEENLY_MAJESTY","name":"Queenly Majesty","effect":"Its majesty pressures the opposing Pokémon, making it unable to attack using priority moves.","pokemon_count":1,"notes":"Imported from Pokemon_Abilities source","source":"https://www.serebii.net/pokedex-champions/","confidenceStatus":"Needs Champions Confirmation","confidenceReason":"Existing local data preserved; official Pokémon Champions confirmation still required before treating as verified.","requiresOfficialReview":true,"strictModeEligible":false},{"ability_id":"ABILITY_QUICK_FEET","name":"Quick Feet","effect":"Boosts Speed if there is a status problem.","pokemon_count":1,"notes":"Imported from Pokemon_Abilities source","source":"https://www.serebii.net/pokedex-champions/","confidenceStatus":"Needs Champions Confirmation","confidenceReason":"Existing local data preserved; official Pokémon Champions confirmation still required before treating as verified.","requiresOfficialReview":true,"strictModeEligible":false},{"ability_id":"ABILITY_RAIN_DISH","name":"Rain Dish","effect":"Slight HP recovery in rain.","pokemon_count":2,"notes":"Imported from Pokemon_Abilities source","source":"https://www.serebii.net/pokedex-champions/","confidenceStatus":"Needs Champions Confirmation","confidenceReason":"Existing local data preserved; official Pokémon Champions confirmation still required before treating as verified.","requiresOfficialReview":true,"strictModeEligible":false},{"ability_id":"ABILITY_RECEIVER","name":"Receiver","effect":"The Pokémon copies the Ability of a defeated ally.","pokemon_count":1,"notes":"Imported from Pokemon_Abilities source","source":"https://www.serebii.net/pokedex-champions/","confidenceStatus":"Needs Champions Confirmation","confidenceReason":"Existing local data preserved; official Pokémon Champions confirmation still required before treating as verified.","requiresOfficialReview":true,"strictModeEligible":false},{"ability_id":"ABILITY_RECKLESS","name":"Reckless","effect":"Powers up moves that have recoil damage.","pokemon_count":2,"notes":"Imported from Pokemon_Abilities source","source":"https://www.serebii.net/pokedex-champions/","confidenceStatus":"Needs Champions Confirmation","confidenceReason":"Existing local data preserved; official Pokémon Champions confirmation still required before treating as verified.","requiresOfficialReview":true,"strictModeEligible":false},{"ability_id":"ABILITY_REFRIGERATE","name":"Refrigerate","effect":"Normal-type moves become Ice-type moves.","pokemon_count":2,"notes":"Imported from Pokemon_Abilities source","source":"https://www.serebii.net/pokedex-champions/","confidenceStatus":"Needs Champions Confirmation","confidenceReason":"Existing local data preserved; official Pokémon Champions confirmation still required before treating as verified.","requiresOfficialReview":true,"strictModeEligible":false},{"ability_id":"ABILITY_REGENERATOR","name":"Regenerator","effect":"Restores a little HP when withdrawn from battle.","pokemon_count":6,"notes":"Imported from Pokemon_Abilities source","source":"https://www.serebii.net/pokedex-champions/","confidenceStatus":"Needs Champions Confirmation","confidenceReason":"Existing local data preserved; official Pokémon Champions confirmation still required before treating as verified.","requiresOfficialReview":true,"strictModeEligible":false},{"ability_id":"ABILITY_RIPEN","name":"Ripen","effect":"Ripens Berries and doubles their effect.","pokemon_count":2,"notes":"Imported from Pokemon_Abilities source","source":"https://www.serebii.net/pokedex-champions/","confidenceStatus":"Needs Champions Confirmation","confidenceReason":"Existing local data preserved; official Pokémon Champions confirmation still required before treating as verified.","requiresOfficialReview":true,"strictModeEligible":false},{"ability_id":"ABILITY_RIVALRY","name":"Rivalry","effect":"Raises Attack if the foe is of the same gender.","pokemon_count":1,"notes":"Imported from Pokemon_Abilities source","source":"https://www.serebii.net/pokedex-champions/","confidenceStatus":"Needs Champions Confirmation","confidenceReason":"Existing local data preserved; official Pokémon Champions confirmation still required before treating as verified.","requiresOfficialReview":true,"strictModeEligible":false},{"ability_id":"ABILITY_ROCK_HEAD","name":"Rock Head","effect":"Protects the Pokémon from recoil damage.","pokemon_count":4,"notes":"Imported from Pokemon_Abilities source","source":"https://www.serebii.net/pokedex-champions/","confidenceStatus":"Needs Champions Confirmation","confidenceReason":"Existing local data preserved; official Pokémon Champions confirmation still required before treating as verified.","requiresOfficialReview":true,"strictModeEligible":false},{"ability_id":"ABILITY_ROUGH_SKIN","name":"Rough Skin","effect":"Hurts to touch.","pokemon_count":2,"notes":"Imported from Pokemon_Abilities source","source":"https://www.serebii.net/pokedex-champions/","confidenceStatus":"Needs Champions Confirmation","confidenceReason":"Existing local data preserved; official Pokémon Champions confirmation still required before treating as verified.","requiresOfficialReview":true,"strictModeEligible":false},{"ability_id":"ABILITY_SAND_FORCE","name":"Sand Force","effect":"Boosts certain moves’ power in a sandstorm.","pokemon_count":4,"notes":"Imported from Pokemon_Abilities source","source":"https://www.serebii.net/pokedex-champions/","confidenceStatus":"Needs Champions Confirmation","confidenceReason":"Existing local data preserved; official Pokémon Champions confirmation still required before treating as verified.","requiresOfficialReview":true,"strictModeEligible":false},{"ability_id":"ABILITY_SAND_RUSH","name":"Sand Rush","effect":"Boosts the Pokémon’s Speed in a sandstorm.","pokemon_count":1,"notes":"Imported from Pokemon_Abilities source","source":"https://www.serebii.net/pokedex-champions/","confidenceStatus":"Needs Champions Confirmation","confidenceReason":"Existing local data preserved; official Pokémon Champions confirmation still required before treating as verified.","requiresOfficialReview":true,"strictModeEligible":false},{"ability_id":"ABILITY_SAND_SPIT","name":"Sand Spit","effect":"The Pokémon creates a sandstorm when it’s hit by an attack.","pokemon_count":1,"notes":"Imported from Pokemon_Abilities source","source":"https://www.serebii.net/pokedex-champions/","confidenceStatus":"Needs Champions Confirmation","confidenceReason":"Existing local data preserved; official Pokémon Champions confirmation still required before treating as verified.","requiresOfficialReview":true,"strictModeEligible":false},{"ability_id":"ABILITY_SAND_STREAM","name":"Sand Stream","effect":"Summons a sandstorm.","pokemon_count":3,"notes":"Imported from Pokemon_Abilities source","source":"https://www.serebii.net/pokedex-champions/","confidenceStatus":"Needs Champions Confirmation","confidenceReason":"Existing local data preserved; official Pokémon Champions confirmation still required before treating as verified.","requiresOfficialReview":true,"strictModeEligible":false},{"ability_id":"ABILITY_SAND_VEIL","name":"Sand Veil","effect":"Ups evasion in a sandstorm.","pokemon_count":6,"notes":"Imported from Pokemon_Abilities source","source":"https://www.serebii.net/pokedex-champions/","confidenceStatus":"Needs Champions Confirmation","confidenceReason":"Existing local data preserved; official Pokémon Champions confirmation still required before treating as verified.","requiresOfficialReview":true,"strictModeEligible":false},{"ability_id":"ABILITY_SAP_SIPPER","name":"Sap Sipper","effect":"Boosts Attack when hit by a Grass-type move.","pokemon_count":5,"notes":"Imported from Pokemon_Abilities source","source":"https://www.serebii.net/pokedex-champions/","confidenceStatus":"Needs Champions Confirmation","confidenceReason":"Existing local data preserved; official Pokémon Champions confirmation still required before treating as verified.","requiresOfficialReview":true,"strictModeEligible":false},{"ability_id":"ABILITY_SCRAPPY","name":"Scrappy","effect":"Enables moves to hit Ghost-type foes.","pokemon_count":3,"notes":"Imported from Pokemon_Abilities source","source":"https://www.serebii.net/pokedex-champions/","confidenceStatus":"Needs Champions Confirmation","confidenceReason":"Existing local data preserved; official Pokémon Champions confirmation still required before treating as verified.","requiresOfficialReview":true,"strictModeEligible":false},{"ability_id":"ABILITY_SCREEN_CLEANER","name":"Screen Cleaner","effect":"When the Pokémon enters a battle, the effects of Light Screen, Reflect, and Aurora Veil are nullified for both opposing and ally Pokémon.","pokemon_count":1,"notes":"Imported from Pokemon_Abilities source","source":"https://www.serebii.net/pokedex-champions/","confidenceStatus":"Needs Champions Confirmation","confidenceReason":"Existing local data preserved; official Pokémon Champions confirmation still required before treating as verified.","requiresOfficialReview":true,"strictModeEligible":false},{"ability_id":"ABILITY_SHADOW_TAG","name":"Shadow Tag","effect":"Prevents the foe’s escape.","pokemon_count":1,"notes":"Imported from Pokemon_Abilities source","source":"https://www.serebii.net/pokedex-champions/","confidenceStatus":"Needs Champions Confirmation","confidenceReason":"Existing local data preserved; official Pokémon Champions confirmation still required before treating as verified.","requiresOfficialReview":true,"strictModeEligible":false},{"ability_id":"ABILITY_SHARPNESS","name":"Sharpness","effect":"Powers up slicing moves.","pokemon_count":3,"notes":"Imported from Pokemon_Abilities source","source":"https://www.serebii.net/pokedex-champions/","confidenceStatus":"Needs Champions Confirmation","confidenceReason":"Existing local data preserved; official Pokémon Champions confirmation still required before treating as verified.","requiresOfficialReview":true,"strictModeEligible":false},{"ability_id":"ABILITY_SHED_SKIN","name":"Shed Skin","effect":"Heals the body by shedding.","pokemon_count":2,"notes":"Imported from Pokemon_Abilities source","source":"https://www.serebii.net/pokedex-champions/","confidenceStatus":"Needs Champions Confirmation","confidenceReason":"Existing local data preserved; official Pokémon Champions confirmation still required before treating as verified.","requiresOfficialReview":true,"strictModeEligible":false},{"ability_id":"ABILITY_SHEER_FORCE","name":"Sheer Force","effect":"Removes added effects to increase move damage.","pokemon_count":8,"notes":"Imported from Pokemon_Abilities source","source":"https://www.serebii.net/pokedex-champions/","confidenceStatus":"Needs Champions Confirmation","confidenceReason":"Existing local data preserved; official Pokémon Champions confirmation still required before treating as verified.","requiresOfficialReview":true,"strictModeEligible":false},{"ability_id":"ABILITY_SHELL_ARMOR","name":"Shell Armor","effect":"Blocks critical hits.","pokemon_count":4,"notes":"Imported from Pokemon_Abilities source","source":"https://www.serebii.net/pokedex-champions/","confidenceStatus":"Needs Champions Confirmation","confidenceReason":"Existing local data preserved; official Pokémon Champions confirmation still required before treating as verified.","requiresOfficialReview":true,"strictModeEligible":false},{"ability_id":"ABILITY_SHIELD_DUST","name":"Shield Dust","effect":"Prevents added effects.","pokemon_count":1,"notes":"Imported from Pokemon_Abilities source","source":"https://www.serebii.net/pokedex-champions/","confidenceStatus":"Needs Champions Confirmation","confidenceReason":"Existing local data preserved; official Pokémon Champions confirmation still required before treating as verified.","requiresOfficialReview":true,"strictModeEligible":false},{"ability_id":"ABILITY_SKILL_LINK","name":"Skill Link","effect":"Increases the frequency of multi-strike moves.","pokemon_count":2,"notes":"Imported from Pokemon_Abilities source","source":"https://www.serebii.net/pokedex-champions/","confidenceStatus":"Needs Champions Confirmation","confidenceReason":"Existing local data preserved; official Pokémon Champions confirmation still required before treating as verified.","requiresOfficialReview":true,"strictModeEligible":false},{"ability_id":"ABILITY_SLUSH_RUSH","name":"Slush Rush","effect":"Boosts the Pokémon’s Speed stat in a hailstorm.","pokemon_count":1,"notes":"Imported from Pokemon_Abilities source","source":"https://www.serebii.net/pokedex-champions/","confidenceStatus":"Needs Champions Confirmation","confidenceReason":"Existing local data preserved; official Pokémon Champions confirmation still required before treating as verified.","requiresOfficialReview":true,"strictModeEligible":false},{"ability_id":"ABILITY_SNIPER","name":"Sniper","effect":"Powers up moves if they become critical hits.","pokemon_count":2,"notes":"Imported from Pokemon_Abilities source","source":"https://www.serebii.net/pokedex-champions/","confidenceStatus":"Needs Champions Confirmation","confidenceReason":"Existing local data preserved; official Pokémon Champions confirmation still required before treating as verified.","requiresOfficialReview":true,"strictModeEligible":false},{"ability_id":"ABILITY_SNOW_CLOAK","name":"Snow Cloak","effect":"Raises evasion in a hailstorm.","pokemon_count":4,"notes":"Imported from Pokemon_Abilities source","source":"https://www.serebii.net/pokedex-champions/","confidenceStatus":"Needs Champions Confirmation","confidenceReason":"Existing local data preserved; official Pokémon Champions confirmation still required before treating as verified.","requiresOfficialReview":true,"strictModeEligible":false},{"ability_id":"ABILITY_SNOW_WARNING","name":"Snow Warning","effect":"The Pokémon summons a hailstorm in battle.","pokemon_count":5,"notes":"Imported from Pokemon_Abilities source","source":"https://www.serebii.net/pokedex-champions/","confidenceStatus":"Needs Champions Confirmation","confidenceReason":"Existing local data preserved; official Pokémon Champions confirmation still required before treating as verified.","requiresOfficialReview":true,"strictModeEligible":false},{"ability_id":"ABILITY_SOLAR_POWER","name":"Solar Power","effect":"Boosts Sp. Atk, but lowers HP in sunshine.","pokemon_count":3,"notes":"Imported from Pokemon_Abilities source","source":"https://www.serebii.net/pokedex-champions/","confidenceStatus":"Needs Champions Confirmation","confidenceReason":"Existing local data preserved; official Pokémon Champions confirmation still required before treating as verified.","requiresOfficialReview":true,"strictModeEligible":false},{"ability_id":"ABILITY_SOLID_ROCK","name":"Solid Rock","effect":"Powers down super­ effective moves.","pokemon_count":2,"notes":"Imported from Pokemon_Abilities source","source":"https://www.serebii.net/pokedex-champions/","confidenceStatus":"Needs Champions Confirmation","confidenceReason":"Existing local data preserved; official Pokémon Champions confirmation still required before treating as verified.","requiresOfficialReview":true,"strictModeEligible":false},{"ability_id":"ABILITY_SOUNDPROOF","name":"Soundproof","effect":"Avoids sound-based moves.","pokemon_count":3,"notes":"Imported from Pokemon_Abilities source","source":"https://www.serebii.net/pokedex-champions/","confidenceStatus":"Needs Champions Confirmation","confidenceReason":"Existing local data preserved; official Pokémon Champions confirmation still required before treating as verified.","requiresOfficialReview":true,"strictModeEligible":false},{"ability_id":"ABILITY_SPEED_BOOST","name":"Speed Boost","effect":"Gradually boosts SPEED.","pokemon_count":2,"notes":"Imported from Pokemon_Abilities source","source":"https://www.serebii.net/pokedex-champions/","confidenceStatus":"Needs Champions Confirmation","confidenceReason":"Existing local data preserved; official Pokémon Champions confirmation still required before treating as verified.","requiresOfficialReview":true,"strictModeEligible":false},{"ability_id":"ABILITY_SPICY_SPRAYNEW","name":"Spicy SprayNEW","effect":"When the Pokémon takes damage from a move, it burns the attacker.","pokemon_count":1,"notes":"Imported from Pokemon_Abilities source","source":"https://www.serebii.net/pokedex-champions/","confidenceStatus":"Needs Champions Confirmation","confidenceReason":"Existing local data preserved; official Pokémon Champions confirmation still required before treating as verified.","requiresOfficialReview":true,"strictModeEligible":false},{"ability_id":"ABILITY_STALL","name":"Stall","effect":"The Pokémon moves after even slower foes.","pokemon_count":1,"notes":"Imported from Pokemon_Abilities source","source":"https://www.serebii.net/pokedex-champions/","confidenceStatus":"Needs Champions Confirmation","confidenceReason":"Existing local data preserved; official Pokémon Champions confirmation still required before treating as verified.","requiresOfficialReview":true,"strictModeEligible":false},{"ability_id":"ABILITY_STALWART","name":"Stalwart","effect":"Ignores the effects of opposing Pokémon’s Abilities and moves that draw in moves.","pokemon_count":2,"notes":"Imported from Pokemon_Abilities source","source":"https://www.serebii.net/pokedex-champions/","confidenceStatus":"Needs Champions Confirmation","confidenceReason":"Existing local data preserved; official Pokémon Champions confirmation still required before treating as verified.","requiresOfficialReview":true,"strictModeEligible":false},{"ability_id":"ABILITY_STAMINA","name":"Stamina","effect":"Boosts the Defense stat when hit by an attack.","pokemon_count":2,"notes":"Imported from Pokemon_Abilities source","source":"https://www.serebii.net/pokedex-champions/","confidenceStatus":"Needs Champions Confirmation","confidenceReason":"Existing local data preserved; official Pokémon Champions confirmation still required before treating as verified.","requiresOfficialReview":true,"strictModeEligible":false},{"ability_id":"ABILITY_STANCE_CHANGE","name":"Stance Change","effect":"The Pokémon changes form depending on how it battles.","pokemon_count":1,"notes":"Imported from Pokemon_Abilities source","source":"https://www.serebii.net/pokedex-champions/","confidenceStatus":"Needs Champions Confirmation","confidenceReason":"Existing local data preserved; official Pokémon Champions confirmation still required before treating as verified.","requiresOfficialReview":true,"strictModeEligible":false},{"ability_id":"ABILITY_STATIC","name":"Static","effect":"Paralyzes on contact.","pokemon_count":7,"notes":"Imported from Pokemon_Abilities source","source":"https://www.serebii.net/pokedex-champions/","confidenceStatus":"Needs Champions Confirmation","confidenceReason":"Existing local data preserved; official Pokémon Champions confirmation still required before treating as verified.","requiresOfficialReview":true,"strictModeEligible":false},{"ability_id":"ABILITY_STEADFAST","name":"Steadfast","effect":"Raises Speed each time the Pokémon flinches.","pokemon_count":3,"notes":"Imported from Pokemon_Abilities source","source":"https://www.serebii.net/pokedex-champions/","confidenceStatus":"Needs Champions Confirmation","confidenceReason":"Existing local data preserved; official Pokémon Champions confirmation still required before treating as verified.","requiresOfficialReview":true,"strictModeEligible":false},{"ability_id":"ABILITY_STENCH","name":"Stench","effect":"Helps repel wild POKéMON.","pokemon_count":1,"notes":"Imported from Pokemon_Abilities source","source":"https://www.serebii.net/pokedex-champions/","confidenceStatus":"Needs Champions Confirmation","confidenceReason":"Existing local data preserved; official Pokémon Champions confirmation still required before treating as verified.","requiresOfficialReview":true,"strictModeEligible":false},{"ability_id":"ABILITY_STICKY_HOLD","name":"Sticky Hold","effect":"Prevents item theft.","pokemon_count":1,"notes":"Imported from Pokemon_Abilities source","source":"https://www.serebii.net/pokedex-champions/","confidenceStatus":"Needs Champions Confirmation","confidenceReason":"Existing local data preserved; official Pokémon Champions confirmation still required before treating as verified.","requiresOfficialReview":true,"strictModeEligible":false},{"ability_id":"ABILITY_STRONG_JAW","name":"Strong Jaw","effect":"The Pokémon’s strong jaw gives it tremendous biting power.","pokemon_count":3,"notes":"Imported from Pokemon_Abilities source","source":"https://www.serebii.net/pokedex-champions/","confidenceStatus":"Needs Champions Confirmation","confidenceReason":"Existing local data preserved; official Pokémon Champions confirmation still required before treating as verified.","requiresOfficialReview":true,"strictModeEligible":false},{"ability_id":"ABILITY_STURDY","name":"Sturdy","effect":"Negates 1-hit KO attacks.","pokemon_count":7,"notes":"Imported from Pokemon_Abilities source","source":"https://www.serebii.net/pokedex-champions/","confidenceStatus":"Needs Champions Confirmation","confidenceReason":"Existing local data preserved; official Pokémon Champions confirmation still required before treating as verified.","requiresOfficialReview":true,"strictModeEligible":false},{"ability_id":"ABILITY_SUPER_LUCK","name":"Super Luck","effect":"Heightens the critical-hit ratios of moves.","pokemon_count":1,"notes":"Imported from Pokemon_Abilities source","source":"https://www.serebii.net/pokedex-champions/","confidenceStatus":"Needs Champions Confirmation","confidenceReason":"Existing local data preserved; official Pokémon Champions confirmation still required before treating as verified.","requiresOfficialReview":true,"strictModeEligible":false},{"ability_id":"ABILITY_SUPERSWEET_SYRUP","name":"Supersweet Syrup","effect":"Lowers the evasion of opposing Pokémon by 1 stage when first sent into battle","pokemon_count":1,"notes":"Imported from Pokemon_Abilities source","source":"https://www.serebii.net/pokedex-champions/","confidenceStatus":"Needs Champions Confirmation","confidenceReason":"Existing local data preserved; official Pokémon Champions confirmation still required before treating as verified.","requiresOfficialReview":true,"strictModeEligible":false},{"ability_id":"ABILITY_SUPREME_OVERLORD","name":"Supreme Overlord","effect":"When the Pokémon enters a battle, its Attack and Sp. Atk stats are slightly boosted for each of the allies in its party that have already been defeated.","pokemon_count":1,"notes":"Imported from Pokemon_Abilities source","source":"https://www.serebii.net/pokedex-champions/","confidenceStatus":"Needs Champions Confirmation","confidenceReason":"Existing local data preserved; official Pokémon Champions confirmation still required before treating as verified.","requiresOfficialReview":true,"strictModeEligible":false},{"ability_id":"ABILITY_SWARM","name":"Swarm","effect":"Ups BUG moves in a pinch.","pokemon_count":6,"notes":"Imported from Pokemon_Abilities source","source":"https://www.serebii.net/pokedex-champions/","confidenceStatus":"Needs Champions Confirmation","confidenceReason":"Existing local data preserved; official Pokémon Champions confirmation still required before treating as verified.","requiresOfficialReview":true,"strictModeEligible":false},{"ability_id":"ABILITY_SWEET_VEIL","name":"Sweet Veil","effect":"Prevents itself and ally Pokémon from falling asleep.","pokemon_count":3,"notes":"Imported from Pokemon_Abilities source","source":"https://www.serebii.net/pokedex-champions/","confidenceStatus":"Needs Champions Confirmation","confidenceReason":"Existing local data preserved; official Pokémon Champions confirmation still required before treating as verified.","requiresOfficialReview":true,"strictModeEligible":false},{"ability_id":"ABILITY_SWIFT_SWIM","name":"Swift Swim","effect":"Raises SPEED in rain.","pokemon_count":1,"notes":"Imported from Pokemon_Abilities source","source":"https://www.serebii.net/pokedex-champions/","confidenceStatus":"Needs Champions Confirmation","confidenceReason":"Existing local data preserved; official Pokémon Champions confirmation still required before treating as verified.","requiresOfficialReview":true,"strictModeEligible":false},{"ability_id":"ABILITY_SYMBIOSIS","name":"Symbiosis","effect":"The Pokémon can pass an item to an ally.","pokemon_count":2,"notes":"Imported from Pokemon_Abilities source","source":"https://www.serebii.net/pokedex-champions/","confidenceStatus":"Needs Champions Confirmation","confidenceReason":"Existing local data preserved; official Pokémon Champions confirmation still required before treating as verified.","requiresOfficialReview":true,"strictModeEligible":false},{"ability_id":"ABILITY_SYNCHRONIZE","name":"Synchronize","effect":"Passes on status problems.","pokemon_count":4,"notes":"Imported from Pokemon_Abilities source","source":"https://www.serebii.net/pokedex-champions/","confidenceStatus":"Needs Champions Confirmation","confidenceReason":"Existing local data preserved; official Pokémon Champions confirmation still required before treating as verified.","requiresOfficialReview":true,"strictModeEligible":false},{"ability_id":"ABILITY_TANGLED_FEET","name":"Tangled Feet","effect":"Raises evasion if the Pokémon is confused.","pokemon_count":2,"notes":"Imported from Pokemon_Abilities source","source":"https://www.serebii.net/pokedex-champions/","confidenceStatus":"Needs Champions Confirmation","confidenceReason":"Existing local data preserved; official Pokémon Champions confirmation still required before treating as verified.","requiresOfficialReview":true,"strictModeEligible":false},{"ability_id":"ABILITY_TECHNICIAN","name":"Technician","effect":"Powers up the Pokémon’s weaker moves.","pokemon_count":4,"notes":"Imported from Pokemon_Abilities source","source":"https://www.serebii.net/pokedex-champions/","confidenceStatus":"Needs Champions Confirmation","confidenceReason":"Existing local data preserved; official Pokémon Champions confirmation still required before treating as verified.","requiresOfficialReview":true,"strictModeEligible":false},{"ability_id":"ABILITY_TELEPATHY","name":"Telepathy","effect":"Anticipates an ally’s attack and dodges it.","pokemon_count":4,"notes":"Imported from Pokemon_Abilities source","source":"https://www.serebii.net/pokedex-champions/","confidenceStatus":"Needs Champions Confirmation","confidenceReason":"Existing local data preserved; official Pokémon Champions confirmation still required before treating as verified.","requiresOfficialReview":true,"strictModeEligible":false},{"ability_id":"ABILITY_THICK_FAT","name":"Thick Fat","effect":"Heat-and-cold protection.","pokemon_count":5,"notes":"Imported from Pokemon_Abilities source","source":"https://www.serebii.net/pokedex-champions/","confidenceStatus":"Needs Champions Confirmation","confidenceReason":"Existing local data preserved; official Pokémon Champions confirmation still required before treating as verified.","requiresOfficialReview":true,"strictModeEligible":false},{"ability_id":"ABILITY_TORRENT","name":"Torrent","effect":"Ups WATER moves in a pinch.","pokemon_count":8,"notes":"Imported from Pokemon_Abilities source","source":"https://www.serebii.net/pokedex-champions/","confidenceStatus":"Needs Champions Confirmation","confidenceReason":"Existing local data preserved; official Pokémon Champions confirmation still required before treating as verified.","requiresOfficialReview":true,"strictModeEligible":false},{"ability_id":"ABILITY_TOUGH_CLAWS","name":"Tough Claws","effect":"Powers up moves that make direct contact.","pokemon_count":2,"notes":"Imported from Pokemon_Abilities source","source":"https://www.serebii.net/pokedex-champions/","confidenceStatus":"Needs Champions Confirmation","confidenceReason":"Existing local data preserved; official Pokémon Champions confirmation still required before treating as verified.","requiresOfficialReview":true,"strictModeEligible":false},{"ability_id":"ABILITY_TOXIC_DEBRIS","name":"Toxic Debris","effect":"Scatters poison spikes at the feet of the opposing team when the Pokémon takes damage from physical moves.","pokemon_count":1,"notes":"Imported from Pokemon_Abilities source","source":"https://www.serebii.net/pokedex-champions/","confidenceStatus":"Needs Champions Confirmation","confidenceReason":"Existing local data preserved; official Pokémon Champions confirmation still required before treating as verified.","requiresOfficialReview":true,"strictModeEligible":false},{"ability_id":"ABILITY_TRACE","name":"Trace","effect":"Copies special ability.","pokemon_count":5,"notes":"Imported from Pokemon_Abilities source","source":"https://www.serebii.net/pokedex-champions/","confidenceStatus":"Needs Champions Confirmation","confidenceReason":"Existing local data preserved; official Pokémon Champions confirmation still required before treating as verified.","requiresOfficialReview":true,"strictModeEligible":false},{"ability_id":"ABILITY_UNAWARE","name":"Unaware","effect":"Ignores any change in ability by the foe.","pokemon_count":2,"notes":"Imported from Pokemon_Abilities source","source":"https://www.serebii.net/pokedex-champions/","confidenceStatus":"Needs Champions Confirmation","confidenceReason":"Existing local data preserved; official Pokémon Champions confirmation still required before treating as verified.","requiresOfficialReview":true,"strictModeEligible":false},{"ability_id":"ABILITY_UNBURDEN","name":"Unburden","effect":"Raises Speed if a held item is used.","pokemon_count":4,"notes":"Imported from Pokemon_Abilities source","source":"https://www.serebii.net/pokedex-champions/","confidenceStatus":"Needs Champions Confirmation","confidenceReason":"Existing local data preserved; official Pokémon Champions confirmation still required before treating as verified.","requiresOfficialReview":true,"strictModeEligible":false},{"ability_id":"ABILITY_UNNERVE","name":"Unnerve","effect":"Makes the foe nervous and unable to eat Berries.","pokemon_count":5,"notes":"Imported from Pokemon_Abilities source","source":"https://www.serebii.net/pokedex-champions/","confidenceStatus":"Needs Champions Confirmation","confidenceReason":"Existing local data preserved; official Pokémon Champions confirmation still required before treating as verified.","requiresOfficialReview":true,"strictModeEligible":false},{"ability_id":"ABILITY_UNSEEN_FIST","name":"Unseen Fist","effect":"If the Pokémon uses moves that make direct contact, it can attack the target even if the target protects itself.","pokemon_count":1,"notes":"Imported from Pokemon_Abilities source","source":"https://www.serebii.net/pokedex-champions/","confidenceStatus":"Needs Champions Confirmation","confidenceReason":"Existing local data preserved; official Pokémon Champions confirmation still required before treating as verified.","requiresOfficialReview":true,"strictModeEligible":false},{"ability_id":"ABILITY_VOLT_ABSORB","name":"Volt Absorb","effect":"Turns electricity into HP.","pokemon_count":1,"notes":"Imported from Pokemon_Abilities source","source":"https://www.serebii.net/pokedex-champions/","confidenceStatus":"Needs Champions Confirmation","confidenceReason":"Existing local data preserved; official Pokémon Champions confirmation still required before treating as verified.","requiresOfficialReview":true,"strictModeEligible":false},{"ability_id":"ABILITY_WANDERING_SPIRIT","name":"Wandering Spirit","effect":"The Pokémon exchanges Abilities with a Pokémon that hits it with a move that makes direct contact.","pokemon_count":1,"notes":"Imported from Pokemon_Abilities source","source":"https://www.serebii.net/pokedex-champions/","confidenceStatus":"Needs Champions Confirmation","confidenceReason":"Existing local data preserved; official Pokémon Champions confirmation still required before treating as verified.","requiresOfficialReview":true,"strictModeEligible":false},{"ability_id":"ABILITY_WATER_ABSORB","name":"Water Absorb","effect":"Restores HP if hit by a Water-type move.","pokemon_count":3,"notes":"Imported from Pokemon_Abilities source","source":"https://www.serebii.net/pokedex-champions/","confidenceStatus":"Needs Champions Confirmation","confidenceReason":"Existing local data preserved; official Pokémon Champions confirmation still required before treating as verified.","requiresOfficialReview":true,"strictModeEligible":false},{"ability_id":"ABILITY_WATER_BUBBLE","name":"Water Bubble","effect":"Lowers the power of Fire-type moves done to the Pokémon and prevents the Pokémon from getting a burn.","pokemon_count":1,"notes":"Imported from Pokemon_Abilities source","source":"https://www.serebii.net/pokedex-champions/","confidenceStatus":"Needs Champions Confirmation","confidenceReason":"Existing local data preserved; official Pokémon Champions confirmation still required before treating as verified.","requiresOfficialReview":true,"strictModeEligible":false},{"ability_id":"ABILITY_WEAK_ARMOR","name":"Weak Armor","effect":"Physical attacks lower Defense and raise Speed.","pokemon_count":6,"notes":"Imported from Pokemon_Abilities source","source":"https://www.serebii.net/pokedex-champions/","confidenceStatus":"Needs Champions Confirmation","confidenceReason":"Existing local data preserved; official Pokémon Champions confirmation still required before treating as verified.","requiresOfficialReview":true,"strictModeEligible":false},{"ability_id":"ABILITY_WHITE_SMOKE","name":"White Smoke","effect":"Prevents ability reduction.","pokemon_count":1,"notes":"Imported from Pokemon_Abilities source","source":"https://www.serebii.net/pokedex-champions/","confidenceStatus":"Needs Champions Confirmation","confidenceReason":"Existing local data preserved; official Pokémon Champions confirmation still required before treating as verified.","requiresOfficialReview":true,"strictModeEligible":false},{"ability_id":"ABILITY_ZERO_TO_HERO","name":"Zero to Hero","effect":"The Pokémon transforms into its Hero Form when it switches out.","pokemon_count":1,"notes":"Imported from Pokemon_Abilities source","source":"https://www.serebii.net/pokedex-champions/","confidenceStatus":"Needs Champions Confirmation","confidenceReason":"Existing local data preserved; official Pokémon Champions confirmation still required before treating as verified.","requiresOfficialReview":true,"strictModeEligible":false},{"ability_id":"ABILITY_SURGE_SURFER","name":"Surge Surfer","effect":"Needs Champions confirmation.","pokemon_count":0,"notes":"Added as form-specific ability placeholder during regional form fill pass.","source":"https://www.serebii.net/pokedex-champions/","confidenceStatus":"Needs Champions Confirmation","confidenceReason":"Referenced by the regional/permanent form species data; Champions-specific validation required.","requiresOfficialReview":true,"strictModeEligible":false},{"ability_id":"ABILITY_QUICK_DRAW","name":"Quick Draw","effect":"Needs Champions confirmation.","pokemon_count":0,"notes":"Added as form-specific ability placeholder during regional form fill pass.","source":"https://www.serebii.net/pokedex-champions/","confidenceStatus":"Needs Champions Confirmation","confidenceReason":"Referenced by the regional/permanent form species data; Champions-specific validation required.","requiresOfficialReview":true,"strictModeEligible":false},{"ability_id":"ABILITY_CURIOUS_MEDICINE","name":"Curious Medicine","effect":"Needs Champions confirmation.","pokemon_count":0,"notes":"Added as form-specific ability placeholder during regional form fill pass.","source":"https://www.serebii.net/pokedex-champions/","confidenceStatus":"Needs Champions Confirmation","confidenceReason":"Referenced by the regional/permanent form species data; Champions-specific validation required.","requiresOfficialReview":true,"strictModeEligible":false},{"ability_id":"ABILITY_MIMICRY","name":"Mimicry","effect":"Needs Champions confirmation.","pokemon_count":0,"notes":"Added as form-specific ability placeholder during regional form fill pass.","source":"https://www.serebii.net/pokedex-champions/","confidenceStatus":"Needs Champions Confirmation","confidenceReason":"Referenced by the regional/permanent form species data; Champions-specific validation required.","requiresOfficialReview":true,"strictModeEligible":false},{"ability_id":"ABILITY_MOLD_BREAKER","name":"Mold Breaker","effect":"Needs Champions confirmation.","pokemon_count":0,"notes":"Added as form-specific ability placeholder during regional form fill pass.","source":"https://www.serebii.net/pokedex-champions/","confidenceStatus":"Needs Champions Confirmation","confidenceReason":"Referenced by the regional/permanent form species data; Champions-specific validation required.","requiresOfficialReview":true,"strictModeEligible":false}]}